utilin/__init__.py
utilin/constants.py
utilin/utils.py
utilin/data/__init__.py
utilin/data/mega_scale_folding_stability.py
utilin/data/proteingym.py
utilin/encode/__init__.py
utilin/encode/one_hot.py
utilin/plotting/__init__.py
utilin/plotting/prediction.py
utilin/splitting/__init__.py
utilin/splitting/splits.py
utilin-0.3.0.dist-info/METADATA
utilin-0.3.0.dist-info/WHEEL
utilin-0.3.0.dist-info/licenses/LICENSE
utilin-0.3.0.dist-info/RECORD
