Metadata-Version: 2.4
Name: utilin
Version: 0.3.0
Summary: Utility package for protein engineering
Author-email: Floris van der Flier <florisvdf@gmail.com>
License-File: LICENSE
Requires-Python: >=3.9
Requires-Dist: biotite>=0.40.0
Requires-Dist: loguru>=0.7.2
Requires-Dist: matplotlib>=3.7.5
Requires-Dist: numpy>1.24.4
Requires-Dist: numpy>=2.0; python_version >= '3.12'
Requires-Dist: pandas>=2.0.3
Requires-Dist: pandas>=2.2.2; python_version >= '3.12'
Requires-Dist: polyleven>=0.8
Requires-Dist: pytest>=8.3.3
Requires-Dist: ruff>=0.6.9
Requires-Dist: scikit-learn>=1.3.2
Requires-Dist: scipy>=1.10.1
Requires-Dist: scipy>=1.14.1; python_version >= '3.12'
Requires-Dist: seaborn>=0.13.2
